django_verify_vat_number/__init__.py
django_verify_vat_number/fetchers.py
django_verify_vat_number/py.typed
django_verify_vat_number/response.py
django_verify_vat_number/settings.py
django_verify_vat_number/urls.py
django_verify_vat_number/locale/cs/LC_MESSAGES/django.mo
django_verify_vat_number/locale/cs/LC_MESSAGES/django.po
django_verify_vat_number/tests/__init__.py
django_verify_vat_number/tests/settings.py
django_verify_vat_number/tests/test_fetchers.py
django_verify_vat_number/tests/test_utils_cache.py
django_verify_vat_number/tests/test_utils_country.py
django_verify_vat_number/tests/test_views_verifiers.py
django_verify_vat_number/tests/urls.py
django_verify_vat_number/utils/__init__.py
django_verify_vat_number/utils/cache.py
django_verify_vat_number/utils/country.py
django_verify_vat_number/views/__init__.py
django_verify_vat_number/views/verifiers.py
django_verify_vat_number-3.1.0.dist-info/METADATA
django_verify_vat_number-3.1.0.dist-info/WHEEL
django_verify_vat_number-3.1.0.dist-info/top_level.txt
django_verify_vat_number-3.1.0.dist-info/RECORD
