Metadata-Version: 2.4
Name: django-verify-vat-number
Version: 3.1.0
Summary: Django Verify VAT number by ARES/VIES
Home-page: https://gitlab.nic.cz/django-apps/django-verify-vat-number/
Author: Zdeněk Böhm
Author-email: zdenek.bohm@nic.cz
License: GPLv3+
Classifier: Typing :: Typed
Classifier: Programming Language :: Python
Classifier: Programming Language :: Python :: 3.9
Classifier: Programming Language :: Python :: 3.10
Classifier: Programming Language :: Python :: 3.11
Classifier: Programming Language :: Python :: 3.12
Classifier: Programming Language :: Python :: 3.13
Classifier: Framework :: Django :: 4.2
Classifier: Framework :: Django :: 5.0
Classifier: Framework :: Django :: 5.1
Classifier: Framework :: Django :: 5.2
Requires-Python: ~=3.9
Requires-Dist: verify-vat-number~=2.0
Requires-Dist: django<5.3,>=4.2
Requires-Dist: django-app-settings>=0.7.1
Requires-Dist: pycountry~=24.0
Provides-Extra: quality
Requires-Dist: doc8; extra == "quality"
Requires-Dist: flake8; extra == "quality"
Requires-Dist: isort; extra == "quality"
Requires-Dist: mypy; extra == "quality"
Requires-Dist: pydocstyle; extra == "quality"
Provides-Extra: test
Requires-Dist: responses; extra == "test"
Requires-Dist: freezegun; extra == "test"
Provides-Extra: types
Requires-Dist: types-requests; extra == "types"
Requires-Dist: types-freezegun; extra == "types"
